langchain_nomic/__init__.py
langchain_nomic/embeddings.py
langchain_nomic/py.typed
langchain_nomic-1.0.1.dist-info/METADATA
langchain_nomic-1.0.1.dist-info/WHEEL
langchain_nomic-1.0.1.dist-info/licenses/LICENSE
langchain_nomic-1.0.1.dist-info/RECORD
