Metadata-Version: 2.4
Name: langchain-nomic
Version: 1.0.1
Summary: An integration package connecting Nomic and LangChain
Project-URL: Homepage, https://docs.langchain.com/oss/python/integrations/providers/nomic
Project-URL: Documentation, https://reference.langchain.com/python/integrations/langchain_nomic/
Project-URL: Source, https://github.com/langchain-ai/langchain/tree/master/libs/partners/nomic
Project-URL: Changelog, https://github.com/langchain-ai/langchain/releases?q=%22langchain-nomic%22
Project-URL: Twitter, https://x.com/LangChainAI
Project-URL: Slack, https://www.langchain.com/join-community
Project-URL: Reddit, https://www.reddit.com/r/LangChain/
License: MIT
License-File: LICENSE
Requires-Python: <4.0.0,>=3.10.0
Requires-Dist: langchain-core<2.0.0,>=1.0.0
Requires-Dist: nomic<4.0.0,>=3.5.3
Requires-Dist: pillow<12.0.0,>=10.3.0
